pyvimond/__init__.py
pyvimond/utils.py
pyvimond/vimond_client.py
pyvimond/vimond_image_service_client.py
tests/__init__.py
tests/test_utils.py
tests/test_vimond_client.py
tests/test_vimond_image_service_client.py
pyvimond-0.5.0.dist-info/LICENSE
pyvimond-0.5.0.dist-info/METADATA
pyvimond-0.5.0.dist-info/WHEEL
pyvimond-0.5.0.dist-info/top_level.txt
pyvimond-0.5.0.dist-info/RECORD
