Metadata-Version: 2.1
Name: pyvimond
Version: 0.5.0
Summary: Tiny client library for various Vimond APIs
Home-page: https://www.mtv.fi/
Author: Sam Stenvall
Author-email: sam.stenvall@nitor.com
License: UNKNOWN
Platform: UNKNOWN
Classifier: Programming Language :: Python :: 3
Classifier: License :: Other/Proprietary License
Classifier: Operating System :: OS Independent
Requires-Python: >=3.6
License-File: LICENSE
Requires-Dist: pycryptodome
Requires-Dist: requests
